mspython/__init__.py
mspython/cloud.py
mspython/cloud_requests.py
mspython/encoder.py
mspython/exceptions.py
mspython/forum.py
mspython/project.py
mspython/session.py
mspython/studio.py
mspython/user.py
mspython-1.0.0.dist-info/LICENSE
mspython-1.0.0.dist-info/METADATA
mspython-1.0.0.dist-info/WHEEL
mspython-1.0.0.dist-info/top_level.txt
mspython-1.0.0.dist-info/RECORD
